easyfasta/__init__.py
easyfasta/easyfata.py
easyfasta-1.0.14.dist-info/METADATA
easyfasta-1.0.14.dist-info/WHEEL
easyfasta-1.0.14.dist-info/licenses/LICENSE
easyfasta-1.0.14.dist-info/RECORD
