Metadata-Version: 2.4
Name: easyfasta
Version: 1.0.14
Summary: A lightweight Python library for efficient FASTA file parsing and DNA sequence manipulation.
Project-URL: Homepage, https://github.com/rLannes/easyfasta
Project-URL: Repository, https://github.com/rLannes/easyfasta
Project-URL: Documentation, https://github.com/rLannes/easyfasta
Author-email: Romain JSB Lannes <romain.lannes@protonmail.com>
Maintainer-email: Romain JSB Lannes <romain.lannes@protonmail.com>
License: MIT
License-File: LICENSE
Keywords: bioinformatics,fasta
Classifier: Development Status :: 5 - Production/Stable
Classifier: License :: OSI Approved :: MIT License
Classifier: Programming Language :: Python :: 3
Classifier: Programming Language :: Python :: 3.8
Classifier: Programming Language :: Python :: 3.9
Classifier: Programming Language :: Python :: 3.10
Classifier: Programming Language :: Python :: 3.11
Classifier: Programming Language :: Python :: 3.12
Classifier: Programming Language :: Python :: 3.13
Requires-Python: >=3.8
